setup.py
distributions2022/Binomialdistribution.py
distributions2022/Gaussiandistribution.py
distributions2022/Generaldistribution.py
distributions2022/__init__.py
distributions2022.egg-info/PKG-INFO
distributions2022.egg-info/SOURCES.txt
distributions2022.egg-info/dependency_links.txt
distributions2022.egg-info/not-zip-safe
distributions2022.egg-info/top_level.txt