Metadata-Version: 1.0
Name: distributions2022
Version: 0.1
Summary: Gaussian distributions and Binomial distributions
Home-page: UNKNOWN
Author: deepa
Author-email: UNKNOWN
License: UNKNOWN
Platform: UNKNOWN
